lru/__init__.py
lru/decorators.py
lru/heap.py
lru/lrucache.py
lru/utils.py
lru/version.py
tests/__init__.py
tests/test_lrucache.py
lruheap-1.0.2.dist-info/LICENSE
lruheap-1.0.2.dist-info/METADATA
lruheap-1.0.2.dist-info/WHEEL
lruheap-1.0.2.dist-info/top_level.txt
lruheap-1.0.2.dist-info/RECORD
