Metadata-Version: 2.1
Name: lruheap
Version: 1.0.2
Summary: Python decorators for store in-data memory using LRU cache
Home-page: https://github.com/sodrooome/lru-cache
Author: Ryan Febriansyah
Author-email: 15523163@students.uii.ac.id
License: MIT
Keywords: cache lru
Platform: UNKNOWN
Classifier: Development Status :: 5 - Production/Stable
Classifier: Environment :: Web Environment
Classifier: Framework :: Django
Classifier: Operating System :: OS Independent
Classifier: Intended Audience :: Developers
Classifier: Natural Language :: English
Classifier: License :: OSI Approved :: MIT License
Classifier: Programming Language :: Python :: 3.5
Classifier: Programming Language :: Python :: 3.6
Classifier: Programming Language :: Python :: 3.7
Requires-Python: >=3.5
